{
  "version": "1.1.1",
  "windows": {
    "main": {
      "main": true,
      "url": "app://editor/index.html",
      "windowType": "dockable",
      "x": 0,
      "y": 23,
      "width": 1440,
      "height": 877,
      "layout": {
        "children": [
          {
            "children": [
              {
                "active": 0,
                "children": [
                  "hierarchy"
                ],
                "height": 462.4375,
                "type": "panel",
                "width": 300.0625
              },
              {
                "active": 0,
                "children": [
                  "assets"
                ],
                "height": 500.5625,
                "type": "panel",
                "width": 300.0625
              }
            ],
            "height": 966,
            "type": "dock-v",
            "width": 300.0625
          },
          {
            "children": [
              {
                "children": [
                  {
                    "active": 0,
                    "children": [
                      "scene"
                    ],
                    "height": 569.4375,
                    "type": "panel",
                    "width": 813.4375
                  },
                  {
                    "active": 0,
                    "children": [
                      "node-library"
                    ],
                    "height": 569.4375,
                    "type": "panel",
                    "width": 300.3125
                  }
                ],
                "height": 569.4375,
                "type": "dock-h",
                "width": 1116.75
              },
              {
                "active": 0,
                "children": [
                  "console",
                  "timeline"
                ],
                "height": 393.5625,
                "type": "panel",
                "width": 1116.75
              }
            ],
            "height": 966,
            "type": "dock-v",
            "width": 1116.75
          },
          {
            "active": 0,
            "children": [
              "inspector"
            ],
            "height": 966,
            "type": "panel",
            "width": 446.1875
          }
        ],
        "type": "dock-h"
      },
      "panels": [
        "console",
        "inspector",
        "hierarchy",
        "assets",
        "scene",
        "node-library",
        "timeline"
      ]
    },
    "worker": {}
  },
  "panels": {
    "code-editor": {
      "x": -1466,
      "y": 214,
      "width": 800,
      "height": 622
    }
  }
}